[
    {
        "num_examples": 1171,
        "batch_size": 32,
        "epochs": 1,
        "lr": 0.01,
        "global_path_norm": 5.925338758771875,
        "local_path_norm": 5.925737133125937,
        "client_data_size": 1171,
        "time": "2024-10-24T22:33:03.549503",
        "model_id": "tmpp33pcw8q.npz"
    },
    {
        "num_examples": 1171,
        "batch_size": 32,
        "epochs": 1,
        "lr": 0.01,
        "global_path_norm": 6.005841987398611,
        "local_path_norm": 5.9984304838941895,
        "client_data_size": 1171,
        "time": "2024-10-24T22:33:12.795140",
        "model_id": "tmpxuwj32e9.npz"
    },
    {
        "num_examples": 1171,
        "batch_size": 32,
        "epochs": 1,
        "lr": 0.01,
        "global_path_norm": 6.1734773897674735,
        "local_path_norm": 6.174852488373615,
        "client_data_size": 1171,
        "time": "2024-10-24T22:33:24.595923",
        "model_id": "tmp86af6t_8.npz"
    },
    {
        "num_examples": 1171,
        "batch_size": 32,
        "epochs": 1,
        "lr": 0.01,
        "global_path_norm": 6.477923168639498,
        "local_path_norm": 6.5075767813280825,
        "client_data_size": 1171,
        "time": "2024-10-24T22:33:33.306901",
        "model_id": "tmpi62vuhjx.npz"
    },
    {
        "num_examples": 1171,
        "batch_size": 32,
        "epochs": 1,
        "lr": 0.01,
        "global_path_norm": 6.824527657062018,
        "local_path_norm": 6.86014849705025,
        "client_data_size": 1171,
        "time": "2024-10-24T22:33:41.738689",
        "model_id": "tmp12fbet09.npz"
    },
    {
        "num_examples": 1171,
        "batch_size": 32,
        "epochs": 1,
        "lr": 0.01,
        "global_path_norm": 7.121222113510687,
        "local_path_norm": 7.155204530001215,
        "client_data_size": 1171,
        "time": "2024-10-24T22:33:51.638286",
        "model_id": "tmp_hnqigl1.npz"
    },
    {
        "num_examples": 1171,
        "batch_size": 32,
        "epochs": 1,
        "lr": 0.01,
        "global_path_norm": 7.370319562321883,
        "local_path_norm": 7.401688470748926,
        "client_data_size": 1171,
        "time": "2024-10-24T22:34:01.179842",
        "model_id": "tmpqitls3_a.npz"
    },
    {
        "num_examples": 1171,
        "batch_size": 32,
        "epochs": 1,
        "lr": 0.01,
        "global_path_norm": 7.5823823591062105,
        "local_path_norm": 7.610167601114526,
        "client_data_size": 1171,
        "time": "2024-10-24T22:34:10.203918",
        "model_id": "tmp7fl7472u.npz"
    },
    {
        "num_examples": 1171,
        "batch_size": 32,
        "epochs": 1,
        "lr": 0.01,
        "global_path_norm": 7.766425477186271,
        "local_path_norm": 7.795312147662349,
        "client_data_size": 1171,
        "time": "2024-10-24T22:34:20.476587",
        "model_id": "tmpf0bufnqv.npz"
    },
    {
        "num_examples": 1171,
        "batch_size": 32,
        "epochs": 1,
        "lr": 0.01,
        "global_path_norm": 7.932698156536943,
        "local_path_norm": 7.956997571226897,
        "client_data_size": 1171,
        "time": "2024-10-24T22:34:30.005810",
        "model_id": "tmpd5wjhv80.npz"
    },
    {
        "num_examples": 1171,
        "batch_size": 32,
        "epochs": 1,
        "lr": 0.01,
        "global_path_norm": 8.084069844411824,
        "local_path_norm": 8.106232374138298,
        "client_data_size": 1171,
        "time": "2024-10-24T22:34:38.821908",
        "model_id": "tmpqzc64qc4.npz"
    },
    {
        "num_examples": 1171,
        "batch_size": 32,
        "epochs": 1,
        "lr": 0.01,
        "global_path_norm": 8.216859781447457,
        "local_path_norm": 8.238316557127103,
        "client_data_size": 1171,
        "time": "2024-10-24T22:34:49.481625",
        "model_id": "tmppk0r71r1.npz"
    },
    {
        "num_examples": 1171,
        "batch_size": 32,
        "epochs": 1,
        "lr": 0.01,
        "global_path_norm": 8.344646448562184,
        "local_path_norm": 8.365760261203091,
        "client_data_size": 1171,
        "time": "2024-10-24T22:34:58.240911",
        "model_id": "tmp3mv4y9a6.npz"
    },
    {
        "num_examples": 1171,
        "batch_size": 32,
        "epochs": 1,
        "lr": 0.01,
        "global_path_norm": 8.46133080974621,
        "local_path_norm": 8.47632060606757,
        "client_data_size": 1171,
        "time": "2024-10-24T22:35:07.826770",
        "model_id": "tmp88o79ozw.npz"
    },
    {
        "num_examples": 1171,
        "batch_size": 32,
        "epochs": 1,
        "lr": 0.01,
        "global_path_norm": 8.57340687446832,
        "local_path_norm": 8.590811487132417,
        "client_data_size": 1171,
        "time": "2024-10-24T22:35:17.015058",
        "model_id": "tmpqj8gg_mp.npz"
    },
    {
        "num_examples": 1171,
        "batch_size": 32,
        "epochs": 1,
        "lr": 0.01,
        "global_path_norm": 8.67504176149018,
        "local_path_norm": 8.693430680664092,
        "client_data_size": 1171,
        "time": "2024-10-24T22:35:26.558130",
        "model_id": "tmppcp65gt6.npz"
    },
    {
        "num_examples": 1171,
        "batch_size": 32,
        "epochs": 1,
        "lr": 0.01,
        "global_path_norm": 8.772238781122653,
        "local_path_norm": 8.78882833889459,
        "client_data_size": 1171,
        "time": "2024-10-24T22:35:34.949207",
        "model_id": "tmp128ucb6k.npz"
    },
    {
        "num_examples": 1171,
        "batch_size": 32,
        "epochs": 1,
        "lr": 0.01,
        "global_path_norm": 8.867070376257038,
        "local_path_norm": 8.878387879102101,
        "client_data_size": 1171,
        "time": "2024-10-24T22:35:44.496488",
        "model_id": "tmpciw9gpu6.npz"
    },
    {
        "num_examples": 1171,
        "batch_size": 32,
        "epochs": 1,
        "lr": 0.01,
        "global_path_norm": 8.958412087264357,
        "local_path_norm": 8.972955335881084,
        "client_data_size": 1171,
        "time": "2024-10-24T22:35:52.714027",
        "model_id": "tmpw18xll8e.npz"
    },
    {
        "num_examples": 1171,
        "batch_size": 32,
        "epochs": 1,
        "lr": 0.01,
        "global_path_norm": 9.04410153373403,
        "local_path_norm": 9.06050982491347,
        "client_data_size": 1171,
        "time": "2024-10-24T22:36:02.132698",
        "model_id": "tmpl_9axii6.npz"
    },
    {
        "num_examples": 1171,
        "batch_size": 32,
        "epochs": 1,
        "lr": 0.01,
        "global_path_norm": 9.12886195565848,
        "local_path_norm": 9.138600286573098,
        "client_data_size": 1171,
        "time": "2024-10-24T22:36:11.812808",
        "model_id": "tmpi_tlg9z3.npz"
    },
    {
        "num_examples": 1171,
        "batch_size": 32,
        "epochs": 1,
        "lr": 0.01,
        "global_path_norm": 9.20364912059395,
        "local_path_norm": 9.213786402086889,
        "client_data_size": 1171,
        "time": "2024-10-24T22:36:21.482916",
        "model_id": "tmpju86m78t.npz"
    },
    {
        "num_examples": 1171,
        "batch_size": 32,
        "epochs": 1,
        "lr": 0.01,
        "global_path_norm": 9.280441916894452,
        "local_path_norm": 9.291280547417317,
        "client_data_size": 1171,
        "time": "2024-10-24T22:36:32.742192",
        "model_id": "tmpdmmnlsca.npz"
    },
    {
        "num_examples": 1171,
        "batch_size": 32,
        "epochs": 1,
        "lr": 0.01,
        "global_path_norm": 9.35467584550959,
        "local_path_norm": 9.366070271122698,
        "client_data_size": 1171,
        "time": "2024-10-24T22:36:43.232241",
        "model_id": "tmph1jd8xfx.npz"
    },
    {
        "num_examples": 1171,
        "batch_size": 32,
        "epochs": 1,
        "lr": 0.01,
        "global_path_norm": 9.425312383114266,
        "local_path_norm": 9.43574820927301,
        "client_data_size": 1171,
        "time": "2024-10-24T22:36:53.058392",
        "model_id": "tmpy0zgja9d.npz"
    },
    {
        "num_examples": 1171,
        "batch_size": 32,
        "epochs": 1,
        "lr": 0.01,
        "global_path_norm": 9.494171060914752,
        "local_path_norm": 9.503918492144294,
        "client_data_size": 1171,
        "time": "2024-10-24T22:37:01.423463",
        "model_id": "tmp7e3rmpqr.npz"
    },
    {
        "num_examples": 1171,
        "batch_size": 32,
        "epochs": 1,
        "lr": 0.01,
        "global_path_norm": 9.56055166304783,
        "local_path_norm": 9.57143587953984,
        "client_data_size": 1171,
        "time": "2024-10-24T22:37:10.728325",
        "model_id": "tmp39l5xfau.npz"
    },
    {
        "num_examples": 1171,
        "batch_size": 32,
        "epochs": 1,
        "lr": 0.01,
        "global_path_norm": 9.629409374532987,
        "local_path_norm": 9.638087107071408,
        "client_data_size": 1171,
        "time": "2024-10-24T22:37:21.875644",
        "model_id": "tmpmfc1ssy8.npz"
    },
    {
        "num_examples": 1171,
        "batch_size": 32,
        "epochs": 1,
        "lr": 0.01,
        "global_path_norm": 9.69395556548591,
        "local_path_norm": 9.699963040625565,
        "client_data_size": 1171,
        "time": "2024-10-24T22:37:31.454846",
        "model_id": "tmp__m0abxf.npz"
    },
    {
        "num_examples": 1171,
        "batch_size": 32,
        "epochs": 1,
        "lr": 0.01,
        "global_path_norm": 9.754439785824623,
        "local_path_norm": 9.761900266232049,
        "client_data_size": 1171,
        "time": "2024-10-24T22:37:40.991725",
        "model_id": "tmp6g36_2m_.npz"
    },
    {
        "num_examples": 1171,
        "batch_size": 32,
        "epochs": 1,
        "lr": 0.01,
        "global_path_norm": 9.814269665573875,
        "local_path_norm": 9.82135067401066,
        "client_data_size": 1171,
        "time": "2024-10-24T22:37:50.328764",
        "model_id": "tmpnim5vaet.npz"
    },
    {
        "num_examples": 1171,
        "batch_size": 32,
        "epochs": 1,
        "lr": 0.01,
        "global_path_norm": 9.87669512528864,
        "local_path_norm": 9.886605890987118,
        "client_data_size": 1171,
        "time": "2024-10-24T22:38:00.229556",
        "model_id": "tmp15vkkbw8.npz"
    },
    {
        "num_examples": 1171,
        "batch_size": 32,
        "epochs": 1,
        "lr": 0.01,
        "global_path_norm": 9.934203746815944,
        "local_path_norm": 9.9412044122438,
        "client_data_size": 1171,
        "time": "2024-10-24T22:38:09.799293",
        "model_id": "tmpc71kir0e.npz"
    },
    {
        "num_examples": 1171,
        "batch_size": 32,
        "epochs": 1,
        "lr": 0.01,
        "global_path_norm": 9.994247593995897,
        "local_path_norm": 10.002668501529442,
        "client_data_size": 1171,
        "time": "2024-10-24T22:38:19.544053",
        "model_id": "tmpl24us91q.npz"
    },
    {
        "num_examples": 1171,
        "batch_size": 32,
        "epochs": 1,
        "lr": 0.01,
        "global_path_norm": 10.049898016113266,
        "local_path_norm": 10.056091827040081,
        "client_data_size": 1171,
        "time": "2024-10-24T22:38:30.215152",
        "model_id": "tmp980serop.npz"
    },
    {
        "num_examples": 1171,
        "batch_size": 32,
        "epochs": 1,
        "lr": 0.01,
        "global_path_norm": 10.105633333603699,
        "local_path_norm": 10.113371493930359,
        "client_data_size": 1171,
        "time": "2024-10-24T22:38:40.444059",
        "model_id": "tmplrlvyf2n.npz"
    },
    {
        "num_examples": 1171,
        "batch_size": 32,
        "epochs": 1,
        "lr": 0.01,
        "global_path_norm": 10.159866956605669,
        "local_path_norm": 10.164510800607859,
        "client_data_size": 1171,
        "time": "2024-10-24T22:38:48.477985",
        "model_id": "tmp9f_t44en.npz"
    },
    {
        "num_examples": 1171,
        "batch_size": 32,
        "epochs": 1,
        "lr": 0.01,
        "global_path_norm": 10.21597569687237,
        "local_path_norm": 10.21997650905231,
        "client_data_size": 1171,
        "time": "2024-10-24T22:38:58.225597",
        "model_id": "tmp01bpnmq7.npz"
    },
    {
        "num_examples": 1171,
        "batch_size": 32,
        "epochs": 1,
        "lr": 0.01,
        "global_path_norm": 10.267483013279278,
        "local_path_norm": 10.273516682946985,
        "client_data_size": 1171,
        "time": "2024-10-24T22:39:08.526493",
        "model_id": "tmpyn201_5p.npz"
    },
    {
        "num_examples": 1171,
        "batch_size": 32,
        "epochs": 1,
        "lr": 0.01,
        "global_path_norm": 10.320640541424876,
        "local_path_norm": 10.324431112286932,
        "client_data_size": 1171,
        "time": "2024-10-24T22:39:18.993515",
        "model_id": "tmpleg5iii7.npz"
    },
    {
        "num_examples": 1171,
        "batch_size": 32,
        "epochs": 1,
        "lr": 0.01,
        "global_path_norm": 10.37179405592285,
        "local_path_norm": 10.378422551769894,
        "client_data_size": 1171,
        "time": "2024-10-24T22:39:30.463939",
        "model_id": "tmpubr6_me3.npz"
    },
    {
        "num_examples": 1171,
        "batch_size": 32,
        "epochs": 1,
        "lr": 0.01,
        "global_path_norm": 10.421380301520333,
        "local_path_norm": 10.425368517027122,
        "client_data_size": 1171,
        "time": "2024-10-24T22:39:39.202621",
        "model_id": "tmpgryr3p6p.npz"
    },
    {
        "num_examples": 1171,
        "batch_size": 32,
        "epochs": 1,
        "lr": 0.01,
        "global_path_norm": 10.472983799457358,
        "local_path_norm": 10.479531273588114,
        "client_data_size": 1171,
        "time": "2024-10-24T22:39:48.227119",
        "model_id": "tmp2xgwn1hb.npz"
    },
    {
        "num_examples": 1171,
        "batch_size": 32,
        "epochs": 1,
        "lr": 0.01,
        "global_path_norm": 10.520786056160535,
        "local_path_norm": 10.524681872998919,
        "client_data_size": 1171,
        "time": "2024-10-24T22:39:57.754097",
        "model_id": "tmpmncrysvn.npz"
    },
    {
        "num_examples": 1171,
        "batch_size": 32,
        "epochs": 1,
        "lr": 0.01,
        "global_path_norm": 10.567066537248486,
        "local_path_norm": 10.57243430755188,
        "client_data_size": 1171,
        "time": "2024-10-24T22:40:08.448019",
        "model_id": "tmpawm848mf.npz"
    },
    {
        "num_examples": 1171,
        "batch_size": 32,
        "epochs": 1,
        "lr": 0.01,
        "global_path_norm": 10.61413458467375,
        "local_path_norm": 10.617350887924884,
        "client_data_size": 1171,
        "time": "2024-10-24T22:40:16.769830",
        "model_id": "tmpk4mllhw7.npz"
    },
    {
        "num_examples": 1171,
        "batch_size": 32,
        "epochs": 1,
        "lr": 0.01,
        "global_path_norm": 10.660015168170265,
        "local_path_norm": 10.664949417960054,
        "client_data_size": 1171,
        "time": "2024-10-24T22:40:26.075784",
        "model_id": "tmporoc_rsn.npz"
    },
    {
        "num_examples": 1171,
        "batch_size": 32,
        "epochs": 1,
        "lr": 0.01,
        "global_path_norm": 10.704702263887198,
        "local_path_norm": 10.7090235585413,
        "client_data_size": 1171,
        "time": "2024-10-24T22:40:35.864926",
        "model_id": "tmpqjap4ei5.npz"
    },
    {
        "num_examples": 1171,
        "batch_size": 32,
        "epochs": 1,
        "lr": 0.01,
        "global_path_norm": 10.751558057853137,
        "local_path_norm": 10.755813002811104,
        "client_data_size": 1171,
        "time": "2024-10-24T22:40:44.945355",
        "model_id": "tmprerdjx8x.npz"
    },
    {
        "num_examples": 1171,
        "batch_size": 32,
        "epochs": 1,
        "lr": 0.01,
        "global_path_norm": 10.796423807391436,
        "local_path_norm": 10.798915201030285,
        "client_data_size": 1171,
        "time": "2024-10-24T22:40:53.367629",
        "model_id": "tmp6rduzmgc.npz"
    }
]